Workbook
Name Risk_Category_List: Lists!$A$1:Lists!$A$10
Name Likelihood_Scale: Lists!$B$1:Lists!$B$5
Name Impact_Scale: Lists!$C$1:Lists!$C$5
Name Control_Effectiveness_List: Lists!$D$1:Lists!$D$4
Name Risk_Response_List: Lists!$E$1:Lists!$E$4
Name Mitigation_Priority_List: Lists!$F$1:Lists!$F$4
Name Status_List_Risks: Lists!$G$1:Lists!$G$5
Name Status_List_Actions: Lists!$H$1:Lists!$H$5
Name Action_Type_List: Lists!$I$1:Lists!$I$9
Name Target_Risk_List: Lists!$J$1:Lists!$J$25

Sheet Lists
A1: Cybersecurity and Information Security | B1: 5 - Very High | C1: 5 - Catastrophic | D1: Effective | E1: Mitigate | F1: Critical | G1: Active | H1: Not Started | I1: Preventive Control | J1: L: 1, I: 1 = Score 1
A2: Operational and Technology | B2: 4 - High | C2: 4 - Major | D2: Partially Effective | E2: Accept | F2: High | G2: Monitoring | H2: In Progress | I2: Detective Control | J2: L: 1, I: 2 = Score 2
A3: Compliance and Regulatory | B3: 3 - Medium | C3: 3 - Moderate | D3: Ineffective | E3: Transfer | F3: Medium | G3: Mitigated | H3: Blocked | I3: Corrective Control | J3: L: 1, I: 3 = Score 3
A4: Third-Party and Vendor | B4: 2 - Low | C4: 2 - Minor | D4: None | E4: Avoid | F4: Low | G4: Accepted | H4: Complete | I4: Risk Transfer | J4: L: 1, I: 4 = Score 4
A5: Business Continuity and Disaster Recovery | B5: 1 - Very Low | C5: 1 - Negligible | G5: Closed | H5: Cancelled | I5: Process Improvement | J5: L: 1, I: 5 = Score 5
A6: Human Capital and Insider | I6: Technical Implementation | J6: L: 2, I: 1 = Score 2
A7: Financial and Fraud | I7: Training/Awareness | J7: L: 2, I: 2 = Score 4
A8: Reputational and Brand | I8: Policy Update | J8: L: 2, I: 3 = Score 6
A9: Strategic and Market | I9: Other | J9: L: 2, I: 4 = Score 8
A10: Physical and Environmental | J10: L: 2, I: 5 = Score 10
J11: L: 3, I: 1 = Score 3
J12: L: 3, I: 2 = Score 6
J13: L: 3, I: 3 = Score 9
J14: L: 3, I: 4 = Score 12
J15: L: 3, I: 5 = Score 15
J16: L: 4, I: 1 = Score 4
J17: L: 4, I: 2 = Score 8
J18: L: 4, I: 3 = Score 12
J19: L: 4, I: 4 = Score 16
J20: L: 4, I: 5 = Score 20
J21: L: 5, I: 1 = Score 5
J22: L: 5, I: 2 = Score 10
... J25: L: 5, I: 5 = Score 25

Sheet Risk_Scenarios
A1: Risk ID | B1: Risk Category | C1: Risk Name | D1: Risk Description | E1: Threat Source | F1: Vulnerabilities | G1: Likelihood (Inherent) | H1: Impact (Inherent) | I1: Inherent Risk Score | J1: Inherent Risk Rating | K1: Existing Controls | L1: Control Effectiveness | M1: Likelihood (Residual) | N1: Impact (Residual) | O1: Residual Risk Score | P1: Residual Risk Rating | Q1: Risk Response Strategy | R1: Risk Owner | S1: Additional Mitigation Needed | T1: Target Residual Risk | U1: Mitigation Priority | V1: Risk Indicators (KRIs) | W1: Last Review Date | X1: Next Review Date | Y1: Status | Z1: Notes
I2: =VALUE(LEFT($G2,1))*VALUE(LEFT($H2,1)) | J2: =IF($I2>=20,"Critical",IF($I2>=15,"High",IF($I2>=10,"Medium",IF($I2>=5,"Low",IF($I2>0,"Very Low",""))))) | O2: =VALUE(LEFT($M2,1))*VALUE(LEFT($N2,1)) | P2: =IF($O2>=20,"Critical",IF($O2>=15,"High",IF($O2>=10,"Medium",IF($O2>=5,"Low",IF($O2>0,"Very Low","")))))
I3: =VALUE(LEFT($G3,1))*VALUE(LEFT($H3,1)) | J3: =IF($I3>=20,"Critical",IF($I3>=15,"High",IF($I3>=10,"Medium",IF($I3>=5,"Low",IF($I3>0,"Very Low",""))))) | O3: =VALUE(LEFT($M3,1))*VALUE(LEFT($N3,1)) | P3: =IF($O3>=20,"Critical",IF($O3>=15,"High",IF($O3>=10,"Medium",IF($O3>=5,"Low",IF($O3>0,"Very Low","")))))
I4: =VALUE(LEFT($G4,1))*VALUE(LEFT($H4,1)) | J4: =IF($I4>=20,"Critical",IF($I4>=15,"High",IF($I4>=10,"Medium",IF($I4>=5,"Low",IF($I4>0,"Very Low",""))))) | O4: =VALUE(LEFT($M4,1))*VALUE(LEFT($N4,1)) | P4: =IF($O4>=20,"Critical",IF($O4>=15,"High",IF($O4>=10,"Medium",IF($O4>=5,"Low",IF($O4>0,"Very Low","")))))
I5: =VALUE(LEFT($G5,1))*VALUE(LEFT($H5,1)) | J5: =IF($I5>=20,"Critical",IF($I5>=15,"High",IF($I5>=10,"Medium",IF($I5>=5,"Low",IF($I5>0,"Very Low",""))))) | O5: =VALUE(LEFT($M5,1))*VALUE(LEFT($N5,1)) | P5: =IF($O5>=20,"Critical",IF($O5>=15,"High",IF($O5>=10,"Medium",IF($O5>=5,"Low",IF($O5>0,"Very Low","")))))
I6: =VALUE(LEFT($G6,1))*VALUE(LEFT($H6,1)) | J6: =IF($I6>=20,"Critical",IF($I6>=15,"High",IF($I6>=10,"Medium",IF($I6>=5,"Low",IF($I6>0,"Very Low",""))))) | O6: =VALUE(LEFT($M6,1))*VALUE(LEFT($N6,1)) | P6: =IF($O6>=20,"Critical",IF($O6>=15,"High",IF($O6>=10,"Medium",IF($O6>=5,"Low",IF($O6>0,"Very Low","")))))
I7: =VALUE(LEFT($G7,1))*VALUE(LEFT($H7,1)) | J7: =IF($I7>=20,"Critical",IF($I7>=15,"High",IF($I7>=10,"Medium",IF($I7>=5,"Low",IF($I7>0,"Very Low",""))))) | O7: =VALUE(LEFT($M7,1))*VALUE(LEFT($N7,1)) | P7: =IF($O7>=20,"Critical",IF($O7>=15,"High",IF($O7>=10,"Medium",IF($O7>=5,"Low",IF($O7>0,"Very Low","")))))
I8: =VALUE(LEFT($G8,1))*VALUE(LEFT($H8,1)) | J8: =IF($I8>=20,"Critical",IF($I8>=15,"High",IF($I8>=10,"Medium",IF($I8>=5,"Low",IF($I8>0,"Very Low",""))))) | O8: =VALUE(LEFT($M8,1))*VALUE(LEFT($N8,1)) | P8: =IF($O8>=20,"Critical",IF($O8>=15,"High",IF($O8>=10,"Medium",IF($O8>=5,"Low",IF($O8>0,"Very Low","")))))
I9: =VALUE(LEFT($G9,1))*VALUE(LEFT($H9,1)) | J9: =IF($I9>=20,"Critical",IF($I9>=15,"High",IF($I9>=10,"Medium",IF($I9>=5,"Low",IF($I9>0,"Very Low",""))))) | O9: =VALUE(LEFT($M9,1))*VALUE(LEFT($N9,1)) | P9: =IF($O9>=20,"Critical",IF($O9>=15,"High",IF($O9>=10,"Medium",IF($O9>=5,"Low",IF($O9>0,"Very Low","")))))
I10: =VALUE(LEFT($G10,1))*VALUE(LEFT($H10,1)) | J10: =IF($I10>=20,"Critical",IF($I10>=15,"High",IF($I10>=10,"Medium",IF($I10>=5,"Low",IF($I10>0,"Very Low",""))))) | O10: =VALUE(LEFT($M10,1))*VALUE(LEFT($N10,1)) | P10: =IF($O10>=20,"Critical",IF($O10>=15,"High",IF($O10>=10,"Medium",IF($O10>=5,"Low",IF($O10>0,"Very Low","")))))
I11: =VALUE(LEFT($G11,1))*VALUE(LEFT($H11,1)) | J11: =IF($I11>=20,"Critical",IF($I11>=15,"High",IF($I11>=10,"Medium",IF($I11>=5,"Low",IF($I11>0,"Very Low",""))))) | O11: =VALUE(LEFT($M11,1))*VALUE(LEFT($N11,1)) | P11: =IF($O11>=20,"Critical",IF($O11>=15,"High",IF($O11>=10,"Medium",IF($O11>=5,"Low",IF($O11>0,"Very Low","")))))
I12: =VALUE(LEFT($G12,1))*VALUE(LEFT($H12,1)) | J12: =IF($I12>=20,"Critical",IF($I12>=15,"High",IF($I12>=10,"Medium",IF($I12>=5,"Low",IF($I12>0,"Very Low",""))))) | O12: =VALUE(LEFT($M12,1))*VALUE(LEFT($N12,1)) | P12: =IF($O12>=20,"Critical",IF($O12>=15,"High",IF($O12>=10,"Medium",IF($O12>=5,"Low",IF($O12>0,"Very Low","")))))
I13: =VALUE(LEFT($G13,1))*VALUE(LEFT($H13,1)) | J13: =IF($I13>=20,"Critical",IF($I13>=15,"High",IF($I13>=10,"Medium",IF($I13>=5,"Low",IF($I13>0,"Very Low",""))))) | O13: =VALUE(LEFT($M13,1))*VALUE(LEFT($N13,1)) | P13: =IF($O13>=20,"Critical",IF($O13>=15,"High",IF($O13>=10,"Medium",IF($O13>=5,"Low",IF($O13>0,"Very Low","")))))
... I1001: =VALUE(LEFT($G1001,1))*VALUE(LEFT($H1001,1)) | J1001: =IF($I1001>=20,"Critical",IF($I1001>=15,"High",IF($I1001>=10,"Medium",IF($I1001>=5,"Low",IF($I1001>0,"Very Low",""))))) | O1001: =VALUE(LEFT($M1001,1))*VALUE(LEFT($N1001,1)) | P1001: =IF($O1001>=20,"Critical",IF($O1001>=15,"High",IF($O1001>=10,"Medium",IF($O1001>=5,"Low",IF($O1001>0,"Very Low","")))))
A1002: RISK-001 | B1002: Cybersecurity and Information Security | C1002: Ransomware Attack on Production Database | D1002: Ransomware malware deployed via phishing email or vulnerability exploit encrypts production database servers, making customer data and core application unavailable. Attackers demand payment for decryption keys. | E1002: External threat actors (cybercriminal groups), potentially insider enabling access | F1002: Unpatched server vulnerabilities; limited email filtering; insufficient endpoint protection; single factor authentication for some admin accounts; limited network segmentation; inadequate backup validation | G1002: 4 - High | H1002: 5 - Catastrophic | I1002: 20 | J1002: Critical | K1002: Email filtering and anti-phishing tools; Endpoint detection and response (EDR) on workstations; Regular vulnerability scanning; Daily backups with 30-day retention; Incident response plan; Security awareness training (quarterly); Network firewall and IDS | L1002: Partially Effective | M1002: 3 - Medium | N1002: 4 - Major | O1002: 12 | P1002: Medium | Q1002: Mitigate | R1002: Michael Rodriguez (CISO) | S1002: Implement mandatory MFA for all admin accounts; Deploy EDR on all servers; Implement network segmentation isolating critical databases; Conduct tabletop exercise for ransomware response; Implement offline/immutable backups; Enhance email security with sandboxing; Accelerate patching cycle to <7 days | T1002: L: 2, I: 3 = Score 6 | U1002: High | V1002: Failed login attempts; Phishing email click rate; Patching compliance %; EDR alert volume; Backup success rate; Mean time to patch | W1002: 45672 | X1002: 45762 | Y1002: Active | Z1002: Similar ransomware attacks affected 3 competitors in past 12 months. Board is monitoring progress quarterly. Cyber insurance renewed with $5M coverage.

Sheet Mitigation_Actions
A1: Action ID | B1: Related Risk ID | C1: Risk Name | D1: Mitigation Action | E1: Action Type | F1: Owner | G1: Priority | H1: Target Completion Date | I1: Status | J1: % Complete | K1: Actual Completion Date | L1: Cost/Budget | M1: Expected Risk Reduction | N1: Effectiveness Validation | O1: Notes

Sheet Risk_Heat_Map
A1: Inherent Risk Heat Map (Likelihood vs Impact)
B2: Impact → | C2: 1 | D2: 2 | E2: 3 | F2: 4 | G2: 5
A3: 5
A4: 4
A5: 3
A6: 2
A7: 1
A9: Tip: Paste Risk IDs into the grid based on Likelihood (rows) and Impact (columns).
A12: Residual Risk Heat Map (Likelihood vs Impact)
B13: Impact → | C13: 1 | D13: 2 | E13: 3 | F13: 4 | G13: 5
A14: 5
A15: 4
A16: 3
A17: 2
A18: 1
A20: Tip: Paste Risk IDs into the grid based on Likelihood (rows) and Impact (columns).
A23: Target Risk Heat Map (Likelihood vs Impact)
B24: Impact → | C24: 1 | D24: 2 | E24: 3 | F24: 4 | G24: 5
A25: 5
A26: 4
A27: 3
A28: 2
A29: 1
A31: Tip: Paste Risk IDs into the grid based on Likelihood (rows) and Impact (columns).

Sheet Risk_Categories_Summary
A1: Risk Category | B1: # of Risks | C1: # Critical/High Risks | D1: Avg Inherent Risk Score | E1: Avg Residual Risk Score | F1: Risk Reduction | G1: % Risk Reduction | H1: # Risks Needing Mitigation | I1: Top 3 Risks
A2: Cybersecurity and Information Security | B2: =COUNTIF(Risk_Scenarios!B:B,A2) | C2: =COUNTIFS(Risk_Scenarios!B:B,A2,Risk_Scenarios!P:P,"Critical")+COUNTIFS(Risk_Scenarios!B:B,A2,Risk_Scenarios!P:P,"High") | D2: =AVERAGEIF(Risk_Scenarios!B:B,A2,Risk_Scenarios!I:I) | E2: =AVERAGEIF(Risk_Scenarios!B:B,A2,Risk_Scenarios!O:O) | F2: =D2-E2 | G2: =IFERROR((D2-E2)/D2*100,"") | H2: =COUNTIFS(Risk_Scenarios!B:B,A2,Risk_Scenarios!U:U,"<>Low",Risk_Scenarios!Y:Y,"Active") | I2: Use filter or pivot to list top risks
A3: Operational and Technology | B3: =COUNTIF(Risk_Scenarios!B:B,A3) | C3: =COUNTIFS(Risk_Scenarios!B:B,A3,Risk_Scenarios!P:P,"Critical")+COUNTIFS(Risk_Scenarios!B:B,A3,Risk_Scenarios!P:P,"High") | D3: =AVERAGEIF(Risk_Scenarios!B:B,A3,Risk_Scenarios!I:I) | E3: =AVERAGEIF(Risk_Scenarios!B:B,A3,Risk_Scenarios!O:O) | F3: =D3-E3 | G3: =IFERROR((D3-E3)/D3*100,"") | H3: =COUNTIFS(Risk_Scenarios!B:B,A3,Risk_Scenarios!U:U,"<>Low",Risk_Scenarios!Y:Y,"Active") | I3: Use filter or pivot to list top risks
A4: Compliance and Regulatory | B4: =COUNTIF(Risk_Scenarios!B:B,A4) | C4: =COUNTIFS(Risk_Scenarios!B:B,A4,Risk_Scenarios!P:P,"Critical")+COUNTIFS(Risk_Scenarios!B:B,A4,Risk_Scenarios!P:P,"High") | D4: =AVERAGEIF(Risk_Scenarios!B:B,A4,Risk_Scenarios!I:I) | E4: =AVERAGEIF(Risk_Scenarios!B:B,A4,Risk_Scenarios!O:O) | F4: =D4-E4 | G4: =IFERROR((D4-E4)/D4*100,"") | H4: =COUNTIFS(Risk_Scenarios!B:B,A4,Risk_Scenarios!U:U,"<>Low",Risk_Scenarios!Y:Y,"Active") | I4: Use filter or pivot to list top risks
A5: Third-Party and Vendor | B5: =COUNTIF(Risk_Scenarios!B:B,A5) | C5: =COUNTIFS(Risk_Scenarios!B:B,A5,Risk_Scenarios!P:P,"Critical")+COUNTIFS(Risk_Scenarios!B:B,A5,Risk_Scenarios!P:P,"High") | D5: =AVERAGEIF(Risk_Scenarios!B:B,A5,Risk_Scenarios!I:I) | E5: =AVERAGEIF(Risk_Scenarios!B:B,A5,Risk_Scenarios!O:O) | F5: =D5-E5 | G5: =IFERROR((D5-E5)/D5*100,"") | H5: =COUNTIFS(Risk_Scenarios!B:B,A5,Risk_Scenarios!U:U,"<>Low",Risk_Scenarios!Y:Y,"Active") | I5: Use filter or pivot to list top risks
A6: Business Continuity and Disaster Recovery | B6: =COUNTIF(Risk_Scenarios!B:B,A6) | C6: =COUNTIFS(Risk_Scenarios!B:B,A6,Risk_Scenarios!P:P,"Critical")+COUNTIFS(Risk_Scenarios!B:B,A6,Risk_Scenarios!P:P,"High") | D6: =AVERAGEIF(Risk_Scenarios!B:B,A6,Risk_Scenarios!I:I) | E6: =AVERAGEIF(Risk_Scenarios!B:B,A6,Risk_Scenarios!O:O) | F6: =D6-E6 | G6: =IFERROR((D6-E6)/D6*100,"") | H6: =COUNTIFS(Risk_Scenarios!B:B,A6,Risk_Scenarios!U:U,"<>Low",Risk_Scenarios!Y:Y,"Active") | I6: Use filter or pivot to list top risks
A7: Human Capital and Insider | B7: =COUNTIF(Risk_Scenarios!B:B,A7) | C7: =COUNTIFS(Risk_Scenarios!B:B,A7,Risk_Scenarios!P:P,"Critical")+COUNTIFS(Risk_Scenarios!B:B,A7,Risk_Scenarios!P:P,"High") | D7: =AVERAGEIF(Risk_Scenarios!B:B,A7,Risk_Scenarios!I:I) | E7: =AVERAGEIF(Risk_Scenarios!B:B,A7,Risk_Scenarios!O:O) | F7: =D7-E7 | G7: =IFERROR((D7-E7)/D7*100,"") | H7: =COUNTIFS(Risk_Scenarios!B:B,A7,Risk_Scenarios!U:U,"<>Low",Risk_Scenarios!Y:Y,"Active") | I7: Use filter or pivot to list top risks
A8: Financial and Fraud | B8: =COUNTIF(Risk_Scenarios!B:B,A8) | C8: =COUNTIFS(Risk_Scenarios!B:B,A8,Risk_Scenarios!P:P,"Critical")+COUNTIFS(Risk_Scenarios!B:B,A8,Risk_Scenarios!P:P,"High") | D8: =AVERAGEIF(Risk_Scenarios!B:B,A8,Risk_Scenarios!I:I) | E8: =AVERAGEIF(Risk_Scenarios!B:B,A8,Risk_Scenarios!O:O) | F8: =D8-E8 | G8: =IFERROR((D8-E8)/D8*100,"") | H8: =COUNTIFS(Risk_Scenarios!B:B,A8,Risk_Scenarios!U:U,"<>Low",Risk_Scenarios!Y:Y,"Active") | I8: Use filter or pivot to list top risks
A9: Reputational and Brand | B9: =COUNTIF(Risk_Scenarios!B:B,A9) | C9: =COUNTIFS(Risk_Scenarios!B:B,A9,Risk_Scenarios!P:P,"Critical")+COUNTIFS(Risk_Scenarios!B:B,A9,Risk_Scenarios!P:P,"High") | D9: =AVERAGEIF(Risk_Scenarios!B:B,A9,Risk_Scenarios!I:I) | E9: =AVERAGEIF(Risk_Scenarios!B:B,A9,Risk_Scenarios!O:O) | F9: =D9-E9 | G9: =IFERROR((D9-E9)/D9*100,"") | H9: =COUNTIFS(Risk_Scenarios!B:B,A9,Risk_Scenarios!U:U,"<>Low",Risk_Scenarios!Y:Y,"Active") | I9: Use filter or pivot to list top risks
A10: Strategic and Market | B10: =COUNTIF(Risk_Scenarios!B:B,A10) | C10: =COUNTIFS(Risk_Scenarios!B:B,A10,Risk_Scenarios!P:P,"Critical")+COUNTIFS(Risk_Scenarios!B:B,A10,Risk_Scenarios!P:P,"High") | D10: =AVERAGEIF(Risk_Scenarios!B:B,A10,Risk_Scenarios!I:I) | E10: =AVERAGEIF(Risk_Scenarios!B:B,A10,Risk_Scenarios!O:O) | F10: =D10-E10 | G10: =IFERROR((D10-E10)/D10*100,"") | H10: =COUNTIFS(Risk_Scenarios!B:B,A10,Risk_Scenarios!U:U,"<>Low",Risk_Scenarios!Y:Y,"Active") | I10: Use filter or pivot to list top risks
A11: Physical and Environmental | B11: =COUNTIF(Risk_Scenarios!B:B,A11) | C11: =COUNTIFS(Risk_Scenarios!B:B,A11,Risk_Scenarios!P:P,"Critical")+COUNTIFS(Risk_Scenarios!B:B,A11,Risk_Scenarios!P:P,"High") | D11: =AVERAGEIF(Risk_Scenarios!B:B,A11,Risk_Scenarios!I:I) | E11: =AVERAGEIF(Risk_Scenarios!B:B,A11,Risk_Scenarios!O:O) | F11: =D11-E11 | G11: =IFERROR((D11-E11)/D11*100,"") | H11: =COUNTIFS(Risk_Scenarios!B:B,A11,Risk_Scenarios!U:U,"<>Low",Risk_Scenarios!Y:Y,"Active") | I11: Use filter or pivot to list top risks

Sheet Executive_Dashboard
A1: Executive Risk Dashboard
A2: Metric | B2: Value | D2: Severity | E2: Count | G2: Category | H2: Count | J2: Metric | K2: Score
A3: Total Risks Identified | B3: =COUNTA(Risk_Scenarios!A:A)-1 | D3: Critical | E3: =B3 | G3: Cybersecurity and Information Security | H3: =COUNTIF(Risk_Scenarios!B:B,"Cybersecurity and Information Security") | J3: Avg Inherent | K3: =B13
A4: Critical Risks (20-25) | B4: =COUNTIF(Risk_Scenarios!O:O,">=20") | D4: High | E4: =B4 | G4: Operational and Technology | H4: =COUNTIF(Risk_Scenarios!B:B,"Operational and Technology") | J4: Avg Residual | K4: =B14
A5: High Risks (15-19) | B5: =COUNTIFS(Risk_Scenarios!O:O,">=15",Risk_Scenarios!O:O,"<20") | D5: Medium | E5: =B5 | G5: Compliance and Regulatory | H5: =COUNTIF(Risk_Scenarios!B:B,"Compliance and Regulatory")
A6: Medium Risks (10-14) | B6: =COUNTIFS(Risk_Scenarios!O:O,">=10",Risk_Scenarios!O:O,"<15") | D6: Low | E6: =B6 | G6: Third-Party and Vendor | H6: =COUNTIF(Risk_Scenarios!B:B,"Third-Party and Vendor")
A7: Low Risks (1-9) | B7: =COUNTIF(Risk_Scenarios!O:O,"<10") | G7: Business Continuity and Disaster Recovery | H7: =COUNTIF(Risk_Scenarios!B:B,"Business Continuity and Disaster Recovery")
A8: Total Mitigation Actions | B8: =COUNTA(Mitigation_Actions!A:A)-1 | G8: Human Capital and Insider | H8: =COUNTIF(Risk_Scenarios!B:B,"Human Capital and Insider")
A9: Actions Complete | B9: =COUNTIF(Mitigation_Actions!I:I,"Complete") | G9: Financial and Fraud | H9: =COUNTIF(Risk_Scenarios!B:B,"Financial and Fraud")
A10: Actions In Progress | B10: =COUNTIF(Mitigation_Actions!I:I,"In Progress") | G10: Reputational and Brand | H10: =COUNTIF(Risk_Scenarios!B:B,"Reputational and Brand")
A11: Actions Not Started | B11: =COUNTIF(Mitigation_Actions!I:I,"Not Started") | G11: Strategic and Market | H11: =COUNTIF(Risk_Scenarios!B:B,"Strategic and Market")
A12: Actions Overdue | B12: =COUNTIFS(Mitigation_Actions!H:H,"<"&TODAY(),Mitigation_Actions!I:I,"<>Complete") | G12: Physical and Environmental | H12: =COUNTIF(Risk_Scenarios!B:B,"Physical and Environmental")
A13: % Mitigation Complete | B13: =IFERROR(B10/B9*100,"")
A14: Avg Inherent Risk Score | B14: =AVERAGE(Risk_Scenarios!I:I)
A15: Avg Residual Risk Score | B15: =AVERAGE(Risk_Scenarios!O:O)
A16: Avg Risk Reduction | B16: =B13-B14
A17: Risks Reviewed This Quarter | B17: =COUNTIFS(Risk_Scenarios!W:W,">="&EOMONTH(TODAY(),-3)+1)
A18: Risks Overdue for Review | B18: =COUNTIF(Risk_Scenarios!X:X,"<"&TODAY())

Sheet Risk_Assessment_History
A1: Risk ID | B1: Assessment Date | C1: Assessment Period | D1: Likelihood (Residual) | E1: Impact (Residual) | F1: Residual Risk Score | G1: Risk Rating | H1: Changes Since Last Assessment | I1: Assessor
F2: =D2*E2 | G2: =IF($F2>=20,"Critical",IF($F2>=15,"High",IF($F2>=10,"Medium",IF($F2>=5,"Low",IF($F2>0,"Very Low","")))))
F3: =D3*E3 | G3: =IF($F3>=20,"Critical",IF($F3>=15,"High",IF($F3>=10,"Medium",IF($F3>=5,"Low",IF($F3>0,"Very Low","")))))
F4: =D4*E4 | G4: =IF($F4>=20,"Critical",IF($F4>=15,"High",IF($F4>=10,"Medium",IF($F4>=5,"Low",IF($F4>0,"Very Low","")))))
F5: =D5*E5 | G5: =IF($F5>=20,"Critical",IF($F5>=15,"High",IF($F5>=10,"Medium",IF($F5>=5,"Low",IF($F5>0,"Very Low","")))))
F6: =D6*E6 | G6: =IF($F6>=20,"Critical",IF($F6>=15,"High",IF($F6>=10,"Medium",IF($F6>=5,"Low",IF($F6>0,"Very Low","")))))
F7: =D7*E7 | G7: =IF($F7>=20,"Critical",IF($F7>=15,"High",IF($F7>=10,"Medium",IF($F7>=5,"Low",IF($F7>0,"Very Low","")))))
F8: =D8*E8 | G8: =IF($F8>=20,"Critical",IF($F8>=15,"High",IF($F8>=10,"Medium",IF($F8>=5,"Low",IF($F8>0,"Very Low","")))))
F9: =D9*E9 | G9: =IF($F9>=20,"Critical",IF($F9>=15,"High",IF($F9>=10,"Medium",IF($F9>=5,"Low",IF($F9>0,"Very Low","")))))
F10: =D10*E10 | G10: =IF($F10>=20,"Critical",IF($F10>=15,"High",IF($F10>=10,"Medium",IF($F10>=5,"Low",IF($F10>0,"Very Low","")))))
F11: =D11*E11 | G11: =IF($F11>=20,"Critical",IF($F11>=15,"High",IF($F11>=10,"Medium",IF($F11>=5,"Low",IF($F11>0,"Very Low","")))))
F12: =D12*E12 | G12: =IF($F12>=20,"Critical",IF($F12>=15,"High",IF($F12>=10,"Medium",IF($F12>=5,"Low",IF($F12>0,"Very Low","")))))
F13: =D13*E13 | G13: =IF($F13>=20,"Critical",IF($F13>=15,"High",IF($F13>=10,"Medium",IF($F13>=5,"Low",IF($F13>0,"Very Low","")))))
... F1001: =D1001*E1001 | G1001: =IF($F1001>=20,"Critical",IF($F1001>=15,"High",IF($F1001>=10,"Medium",IF($F1001>=5,"Low",IF($F1001>0,"Very Low","")))))

Sheet Risk_Scenario_Templates
A1: Risk ID | B1: Risk Category | C1: Risk Name | D1: Risk Description | E1: Threat Source | F1: Vulnerabilities | G1: Likelihood (Inherent) | H1: Impact (Inherent) | I1: Inherent Risk Score | J1: Inherent Risk Rating | K1: Existing Controls | L1: Control Effectiveness | M1: Likelihood (Residual) | N1: Impact (Residual) | O1: Residual Risk Score | P1: Residual Risk Rating | Q1: Risk Response Strategy | R1: Risk Owner | S1: Additional Mitigation Needed | T1: Target Residual Risk | U1: Mitigation Priority | V1: Risk Indicators (KRIs) | W1: Last Review Date | X1: Next Review Date | Y1: Status | Z1: Notes
A2: TEMP-001 | B2: Cybersecurity and Information Security | C2: Ransomware attack encrypting critical systems | Y2: Monitoring
A3: TEMP-002 | B3: Cybersecurity and Information Security | C3: Phishing attack compromising employee credentials | Y3: Monitoring
A4: TEMP-003 | B4: Business Continuity and Disaster Recovery | C4: Cloud provider outage causing service disruption | Y4: Monitoring
A5: TEMP-004 | B5: Third-Party and Vendor | C5: Critical vendor data breach affecting our data | Y5: Monitoring
A6: TEMP-005 | B6: Human Capital and Insider | C6: Insider threat exfiltrating sensitive data | Y6: Monitoring
A7: TEMP-006 | B7: Operational and Technology | C7: Failed system migration causing extended outage | Y7: Monitoring
A8: TEMP-007 | B8: Compliance and Regulatory | C8: GDPR non-compliance resulting in regulatory fines | Y8: Monitoring
A9: TEMP-008 | B9: Human Capital and Insider | C9: Key personnel departure taking critical knowledge | Y9: Monitoring
A10: TEMP-009 | B10: Physical and Environmental | C10: Natural disaster destroying primary data center | Y10: Monitoring
A11: TEMP-010 | B11: Cybersecurity and Information Security | C11: DDoS attack making services unavailable | Y11: Monitoring
A12: TEMP-011 | B12: Cybersecurity and Information Security | C12: Privilege escalation via misconfigured IAM | Y12: Monitoring
A13: TEMP-012 | B13: Cybersecurity and Information Security | C13: Compromised API keys used for data extraction | Y13: Monitoring
... A26: TEMP-025 | B26: Operational and Technology | C26: Change failure causing production rollback | Y26: Monitoring
